README.md
setup.py
smartsifter.py
smartsifter.egg-info/PKG-INFO
smartsifter.egg-info/SOURCES.txt
smartsifter.egg-info/dependency_links.txt
smartsifter.egg-info/requires.txt
smartsifter.egg-info/top_level.txt